{
  "main": {
    "id": "1cb3d8e04088ba87",
    "type": "split",
    "children": [
      {
        "id": "c71bac60e72b6081",
        "type": "tabs",
        "children": [
          {
            "id": "ca4eb36ef24bf040",
            "type": "leaf",
            "state": {
              "type": "markdown",
              "state": {
                "file": "node.js/패키지 매니저/Yarn Berry Dockerizing.md",
                "mode": "source",
                "source": false
              }
            }
          },
          {
            "id": "5c5cc358038a63f7",
            "type": "leaf",
            "state": {
              "type": "markdown",
              "state": {
                "file": "devops/docker/docker compose 명령어 모음.md",
                "mode": "source",
                "source": false
              }
            }
          },
          {
            "id": "a19605ed1d65364d",
            "type": "leaf",
            "state": {
              "type": "markdown",
              "state": {
                "file": "computer science/network/로드 밸런싱 개념.md",
                "mode": "source",
                "source": false
              }
            }
          },
          {
            "id": "508f283b027473d0",
            "type": "leaf",
            "state": {
              "type": "markdown",
              "state": {
                "file": "typescript/logging.md",
                "mode": "source",
                "source": false
              }
            }
          },
          {
            "id": "b0db135253277391",
            "type": "leaf",
            "state": {
              "type": "markdown",
              "state": {
                "file": "node.js/패키지 매니저/yarn.md",
                "mode": "source",
                "source": false
              }
            }
          },
          {
            "id": "e87fdd907f14cffa",
            "type": "leaf",
            "state": {
              "type": "markdown",
              "state": {
                "file": "mongo/mongo.md",
                "mode": "source",
                "source": false
              }
            }
          },
          {
            "id": "8f2d783736861a78",
            "type": "leaf",
            "state": {
              "type": "markdown",
              "state": {
                "file": "mysql/GROUP BY.md",
                "mode": "source",
                "source": false
              }
            }
          },
          {
            "id": "9278a6cb3fcd9e6e",
            "type": "leaf",
            "state": {
              "type": "markdown",
              "state": {
                "file": "mysql/Join.md",
                "mode": "source",
                "source": false
              }
            }
          },
          {
            "id": "1b267d4625763b0d",
            "type": "leaf",
            "state": {
              "type": "markdown",
              "state": {
                "file": "blockchain/스테이킹.md",
                "mode": "source",
                "source": false
              }
            }
          },
          {
            "id": "9d857c268bac416c",
            "type": "leaf",
            "state": {
              "type": "markdown",
              "state": {
                "file": "blockchain/이더리움/EOA, CA.md",
                "mode": "source",
                "source": false
              }
            }
          },
          {
            "id": "d75642b90339129f",
            "type": "leaf",
            "state": {
              "type": "markdown",
              "state": {
                "file": "blockchain/이더리움/트랜잭션 종류.md",
                "mode": "source",
                "source": false
              }
            }
          }
        ],
        "currentTab": 10
      }
    ],
    "direction": "vertical"
  },
  "left": {
    "id": "c025c08dbd0019d0",
    "type": "split",
    "children": [
      {
        "id": "068eec4e387fe1eb",
        "type": "tabs",
        "children": [
          {
            "id": "fe4df59a143d7373",
            "type": "leaf",
            "state": {
              "type": "file-explorer",
              "state": {
                "sortOrder": "alphabetical"
              }
            }
          },
          {
            "id": "48629f613380c07b",
            "type": "leaf",
            "state": {
              "type": "search",
              "state": {
                "query": "",
                "matchingCase": false,
                "explainSearch": false,
                "collapseAll": false,
                "extraContext": false,
                "sortOrder": "alphabetical"
              }
            }
          },
          {
            "id": "668511922a48e1b8",
            "type": "leaf",
            "state": {
              "type": "starred",
              "state": {}
            }
          }
        ]
      }
    ],
    "direction": "horizontal",
    "width": 300
  },
  "right": {
    "id": "6bfc3be2b3864dbe",
    "type": "split",
    "children": [
      {
        "id": "06242139d255f0c7",
        "type": "tabs",
        "children": [
          {
            "id": "1a0b1b46c3bdf2aa",
            "type": "leaf",
            "state": {
              "type": "backlink",
              "state": {
                "file": "blockchain/이더리움/트랜잭션 종류.md",
                "collapseAll": false,
                "extraContext": false,
                "sortOrder": "alphabetical",
                "showSearch": false,
                "searchQuery": "",
                "backlinkCollapsed": false,
                "unlinkedCollapsed": true
              }
            }
          },
          {
            "id": "5b949c25633867a1",
            "type": "leaf",
            "state": {
              "type": "outgoing-link",
              "state": {
                "file": "blockchain/이더리움/트랜잭션 종류.md",
                "linksCollapsed": false,
                "unlinkedCollapsed": true
              }
            }
          },
          {
            "id": "2d763f3d5c8eec63",
            "type": "leaf",
            "state": {
              "type": "tag",
              "state": {
                "sortOrder": "frequency",
                "useHierarchy": true
              }
            }
          },
          {
            "id": "f3649eae8a925dfe",
            "type": "leaf",
            "state": {
              "type": "outline",
              "state": {
                "file": "blockchain/이더리움/트랜잭션 종류.md"
              }
            }
          },
          {
            "id": "eb6d476d15e97f7b",
            "type": "leaf",
            "state": {
              "type": "advanced-tables-toolbar",
              "state": {}
            }
          }
        ],
        "currentTab": 4
      }
    ],
    "direction": "horizontal",
    "width": 300
  },
  "left-ribbon": {
    "hiddenItems": {
      "switcher:퀵 스위처 열기": false,
      "graph:그래프 뷰 열기": false,
      "canvas:새 캔버스 만들기": false,
      "daily-notes:오늘의 데일리 노트 열기": false,
      "templates:템플릿 삽입": false,
      "command-palette:명령어 팔레트 열기": false,
      "templater-obsidian:Templater": false,
      "obsidian-excalidraw-plugin:Create new drawing": false,
      "obsidian-full-calendar:Open Full Calendar": false,
      "table-editor-obsidian:Advanced Tables Toolbar": false
    }
  },
  "active": "d75642b90339129f",
  "lastOpenFiles": [
    "typeorm/무제 파일.md",
    "blockchain/블록체인.md",
    "blockchain/이더리움/이더리움 계정.md",
    "blockchain/이더리움/트랜잭션 종류.md",
    "blockchain/이더리움/EOA, CA.md",
    "blockchain/스테이킹.md",
    "aws",
    "mysql/Join.md",
    "mysql/GROUP BY.md",
    "mongo/mongo.md",
    "node.js/패키지 매니저/yarn.md",
    "mongo",
    "typescript/logging.md",
    "typescript/주석 가이드.md",
    "computer science/network/로드 밸런싱 개념.md",
    "node.js/패키지 매니저/Yarn Berry Dockerizing.md",
    "devops/docker/docker 기초.md",
    "devops/docker/docker 명령어 모음.md",
    "devops/docker/setenv The parameter is incorrect 에러.md",
    "typescript/error handling.md",
    "README.md",
    "javascript/주석 간지나게 쓰는법 feat. JSDoc.md",
    "conflict-files-obsidian-git.md",
    "devops/git/secret 값을 커밋했을 때 되돌리는 방법.md",
    "typeorm/Entity metadata for anything was not found 에러 해결.md",
    "typeorm/Query Builder에서 Conditional Clauses 쓰기.md",
    "typeorm",
    "node.js/모듈 시스템.md",
    "[Promise.all().md",
    "devops",
    "computer science/algorithm",
    "computer science/data structure",
    "computer science/computer architecture",
    "computer science/os",
    "computer science",
    "nestjs",
    "ZipFs.png",
    "무제 파일.canvas",
    "무제 파일 1.canvas",
    "무제 파일 4.canvas",
    "무제 파일 3.canvas",
    "무제 파일 2.canvas"
  ]
}